pg_lock_tracer/__init__.py
pg_lock_tracer/animate_lock_graph.py
pg_lock_tracer/helper.py
pg_lock_tracer/oid_resolver.py
pg_lock_tracer/pg_lock_tracer.py
pg_lock_tracer/pg_lw_lock_tracer.py
pg_lock_tracer/pg_row_lock_tracer.py
pg_lock_tracer/bpf/__init__.py
pg_lock_tracer/bpf/pg_lock_tracer.c
pg_lock_tracer/bpf/pg_lw_lock_tracer.c
pg_lock_tracer/bpf/pg_row_lock_tracer.c
pg_lock_tracer-0.6.2.dist-info/LICENSE
pg_lock_tracer-0.6.2.dist-info/METADATA
pg_lock_tracer-0.6.2.dist-info/WHEEL
pg_lock_tracer-0.6.2.dist-info/entry_points.txt
pg_lock_tracer-0.6.2.dist-info/top_level.txt
pg_lock_tracer-0.6.2.dist-info/RECORD
