Metadata-Version: 2.1
Name: pg_lock_tracer
Version: 0.6.2
Summary: A BPF based lock tracer for the PostgreSQL database
Home-page: https://github.com/jnidzwetzki/pg-lock-tracer
Author: Jan Nidzwetzki
Project-URL: Bug Tracker, https://github.com/jnidzwetzki/pg-lock-tracer/issues
Keywords: postgresql bpf lock locktracer
Classifier: Development Status :: 4 - Beta
Classifier: Intended Audience :: Developers
Classifier: Operating System :: POSIX :: Linux
Classifier: Programming Language :: Python
Classifier: Topic :: Software Development :: Debuggers
Classifier: License :: OSI Approved :: Apache Software License
Requires-Python: >=3.6
License-File: LICENSE
Requires-Dist: graphviz
Requires-Dist: igraph
Requires-Dist: prettytable
Requires-Dist: psycopg2
